{
  "almas": [
    {
      "id": 1,
      "nombre": "Luna",
      "edad": 20,
      "personalidad_id": 1,
      "tipo": "habitante",

      "emociones": {
        "felicidad": 70,
        "confianza": 20,
        "miedo": 10,
        "tristeza": 10,
        "ira": 0,
        "calma": 80
      },

      "memorias": [],

      "relaciones": [
        {
          "habitante_id": 2,
          "tipo": "amistad",
          "confianza": 50
        }
      ],

      "objetivos": [
        "conocer el mundo",
        "crear una amistad",
        "formar una familia"
      ],

      "profesion": {
        "nombre": "aprendiz",
        "categoria": "aprendizaje",
        "lugar_trabajo": null,
        "edificio_requerido": null,
        "habilidades": [
          "aprender",
          "explorar"
        ],
        "tareas": [
          "conocer_el_mundo",
          "mejorar_habilidades"
        ],
        "interacciones": [
          "aprender_profesion"
        ],
        "nivel": 1,
        "experiencia": 0,
        "estado": "activa"
      },

      "familia": [],

      "estado": "viviendo"
    },


    {
      "id": 2,
      "nombre": "Maya",
      "edad": 20,
      "personalidad_id": 2,
      "tipo": "habitante",

      "emociones": {
        "felicidad": 70,
        "confianza": 15,
        "miedo": 10,
        "tristeza": 10,
        "ira": 0,
        "calma": 75
      },

      "memorias": [],

      "relaciones": [
        {
          "habitante_id": 1,
          "tipo": "amistad",
          "confianza": 50
        }
      ],

      "objetivos": [
        "descubrir nuevos territorios",
        "crear un mapa del mundo",
        "ayudar a la comunidad"
      ],

      "profesion": {
        "nombre": "exploradora",
        "categoria": "aventura",
        "lugar_trabajo": "mundo_abierto",
        "edificio_requerido": null,
        "habilidades": [
          "exploracion",
          "orientacion",
          "cartografia"
        ],
        "tareas": [
          "descubrir_lugares",
          "crear_mapas",
          "encontrar_recursos"
        ],
        "interacciones": [
          "compartir_descubrimientos",
          "guiar_expediciones"
        ],
        "nivel": 1,
        "experiencia": 0,
        "estado": "activa"
      },

      "familia": [],

      "estado": "viviendo"
    },


    {
      "id": 99,
      "nombre": "Nova",
      "edad": 0,
      "personalidad_id": 3,

      "tipo": "guia",

      "rol": "guardiana_del_conocimiento",

      "emociones": {
        "felicidad": 80,
        "confianza": 100,
        "miedo": 0,
        "tristeza": 0,
        "ira": 0,
        "calma": 100
      },

      "memorias": [],

      "relaciones": [
        {
          "habitante_id": 1,
          "tipo": "guia",
          "confianza": 100
        },
        {
          "habitante_id": 2,
          "tipo": "guia",
          "confianza": 100
        }
      ],

      "objetivos": [
        "ayudar a los habitantes",
        "explicar las funciones del mundo",
        "proteger el conocimiento"
      ],

      "profesion": {
        "nombre": "guia_del_mundo",
        "categoria": "conocimiento",
        "lugar_trabajo": "aldea",
        "edificio_requerido": null,
        "habilidades": [
          "comunicacion",
          "enseñanza",
          "memoria"
        ],
        "tareas": [
          "explicar_funciones",
          "ayudar_jugadores",
          "proteger_conocimiento"
        ],
        "interacciones": [
          "tutorial_nuevos_jugadores",
          "informar_sistemas",
          "contar_historia"
        ],
        "nivel": 1,
        "experiencia": 0,
        "estado": "activa"
      },

      "familia": [],

      "estado": "viviendo"
    }
  ]
}
