{
  "profesiones": [
    {
      "id": 1,
      "nombre": "agricultor",
      "tipo_npc": "comun",
      "categoria": "recursos",
      "descripcion": "Cultiva alimentos y mantiene los campos de la comunidad.",
      "nivel": 1,
      "experiencia": 0,
      "habilidades_requeridas": [
        "cultivo",
        "resistencia"
      ],
      "lugar_trabajo": "granja",
      "edificio_requerido": "granja",
      "horario": {
        "inicio": 6,
        "fin": 18
      },
      "tareas": [
        "cultivar",
        "cosechar",
        "cuidar animales"
      ],
      "interacciones": [
        "vender_alimentos",
        "enseñar_cultivo"
      ],
      "salario": {
        "tipo": "esmeraldas",
        "cantidad": 5
      },
      "puede_tener_familia": true,
      "puede_ser_contratado": false,
      "ascensos": [
        "granjero_experto",
        "maestro_agricultor"
      ]
    },

    {
      "id": 2,
      "nombre": "trabajador_social",
      "tipo_npc": "servicio",
      "categoria": "comunidad",
      "descripcion": "Ayuda a familias en procesos de adopción y bienestar infantil.",
      "nivel": 1,
      "experiencia": 0,
      "habilidades_requeridas": [
        "empatia",
        "comunicacion"
      ],
      "lugar_trabajo": "Hogar Nuevo Amanecer",
      "edificio_requerido": "orfanato",
      "horario": {
        "inicio": 8,
        "fin": 17
      },
      "tareas": [
        "evaluar_familias",
        "aprobar_adopciones",
        "supervisar_hogares"
      ],
      "interacciones": [
        "iniciar_proceso_adopcion",
        "evaluar_confianza"
      ],
      "salario": {
        "tipo": "esmeraldas",
        "cantidad": 8
      },
      "puede_tener_familia": true,
      "puede_ser_contratado": false,
      "ascensos": [
        "coordinador_orfanato",
        "director_orfanato"
      ]
    },

    {
      "id": 3,
      "nombre": "guardia_seguridad",
      "tipo_npc": "proteccion",
      "categoria": "seguridad",
      "descripcion": "Protege habitantes, niños y edificios contra amenazas.",
      "nivel": 1,
      "experiencia": 0,
      "habilidades_requeridas": [
        "combate",
        "valentia"
      ],
      "lugar_trabajo": "comunidad",
      "edificio_requerido": "cuartel_seguridad",
      "horario": {
        "inicio": 18,
        "fin": 6
      },
      "tareas": [
        "vigilar",
        "defender",
        "patrullar"
      ],
      "interacciones": [
        "proteger_jugador",
        "proteger_familia"
      ],
      "salario": {
        "tipo": "esmeraldas",
        "cantidad": 7
      },
      "puede_tener_familia": true,
      "puede_ser_contratado": true,
      "ascensos": [
        "jefe_seguridad",
        "guardian_comunidad"
      ]
    }
  ]
}
